uvc/__init__.py
uvc/py.typed
uvc/uvc_ext.cpython-312-x86_64-linux-gnu.so
uvc/uvc_ext.pyi
uvc_py-2026.1.0.dev0.dist-info/METADATA
uvc_py-2026.1.0.dev0.dist-info/WHEEL
uvc_py-2026.1.0.dev0.dist-info/RECORD
uvc_py-2026.1.0.dev0.dist-info/licenses/LICENSE
