Metadata-Version: 2.4
Name: uvc-py
Version: 2026.1.0.dev0
Summary: Cross-platform UVC camera library binding for Python
Author-Email: "Shiguredo Inc." <contact+pypi@shiguredo.jp>
License-Expression: Apache-2.0
License-File: LICENSE
Classifier: Programming Language :: Python :: 3
Classifier: Programming Language :: Python :: 3 :: Only
Classifier: Programming Language :: Python :: 3.12
Classifier: Programming Language :: Python :: 3.13
Classifier: Programming Language :: Python :: 3.14
Classifier: Programming Language :: Python :: Free Threading :: 2 - Beta
Classifier: Programming Language :: C++
Classifier: Operating System :: MacOS :: MacOS X
Classifier: Operating System :: POSIX :: Linux
Project-URL: Source, https://github.com/shiguredo/uvc-py
Project-URL: Discord, https://discord.gg/shiguredo
Requires-Python: >=3.12
